findconfig/__init__.py
findconfig/findconfig.py
findconfig-1.3.dist-info/LICENSE.txt
findconfig-1.3.dist-info/METADATA
findconfig-1.3.dist-info/WHEEL
findconfig-1.3.dist-info/top_level.txt
findconfig-1.3.dist-info/RECORD
