Metadata-Version: 2.1
Name: findconfig
Version: 1.3
Summary: Find a config file in XDG paths, home or calling package path
Home-page: https://github.com/ggonnella/findconfig
Author: Giorgio Gonnella
Author-email: gonnella@zbh.uni-hamburg.de
License: ISC
Keywords: configuration xdg
Classifier: Development Status :: 5 - Production/Stable
Classifier: Environment :: Console
Classifier: Intended Audience :: Developers
Classifier: Intended Audience :: End Users/Desktop
Classifier: Intended Audience :: Science/Research
Classifier: License :: OSI Approved :: ISC License (ISCL)
Classifier: Operating System :: MacOS :: MacOS X
Classifier: Operating System :: POSIX :: Linux
Classifier: Programming Language :: Python :: 3 :: Only
Classifier: Topic :: Software Development :: Libraries
License-File: LICENSE.txt
Requires-Dist: xdg
